{
  "__inputs": [],
  "__requires": [
    { "type": "grafana", "id": "grafana", "name": "Grafana", "version": "10.0.0" },
    { "type": "datasource", "id": "prometheus", "name": "Prometheus", "version": "1.0.0" }
  ],
  "annotations": {
    "list": [
      {
        "builtIn": 1,
        "datasource": { "type": "grafana", "uid": "-- Grafana --" },
        "enable": true,
        "hide": true,
        "iconColor": "rgba(0, 211, 255, 1)",
        "name": "Annotations & Alerts",
        "type": "dashboard"
      },
      {
        "datasource": { "type": "prometheus", "uid": "prometheus" },
        "enable": true,
        "expr": "increase(dg_tier_transitions_total[1m]) > 0",
        "hide": false,
        "iconColor": "#FF0000",
        "name": "Tier Transitions",
        "step": "60s",
        "titleFormat": "Tier change",
        "type": "graph"
      }
    ]
  },
  "description": "IDDC — Intent-Driven Degradation Contracts monitoring dashboard",
  "editable": true,
  "fiscalYearStartMonth": 0,
  "graphTooltip": 1,
  "id": null,
  "links": [],
  "panels": [
    {
      "collapsed": false,
      "gridPos": { "h": 1, "w": 24, "x": 0, "y": 0 },
      "id": 100,
      "title": "Overview",
      "type": "row"
    },
    {
      "datasource": { "type": "prometheus", "uid": "prometheus" },
      "fieldConfig": {
        "defaults": {
          "color": { "mode": "thresholds" },
          "mappings": [
            { "options": { "0": { "color": "green", "index": 0, "text": "nominal" } }, "type": "value" },
            { "options": { "1": { "color": "yellow", "index": 1, "text": "warm" } }, "type": "value" },
            { "options": { "2": { "color": "orange", "index": 2, "text": "hot" } }, "type": "value" },
            { "options": { "3": { "color": "red", "index": 3, "text": "critical" } }, "type": "value" },
            { "options": { "4": { "color": "dark-red", "index": 4, "text": "survival" } }, "type": "value" }
          ],
          "thresholds": {
            "mode": "absolute",
            "steps": [
              { "color": "green", "value": null },
              { "color": "yellow", "value": 1 },
              { "color": "orange", "value": 2 },
              { "color": "red", "value": 3 },
              { "color": "dark-red", "value": 4 }
            ]
          },
          "unit": "short"
        },
        "overrides": []
      },
      "gridPos": { "h": 6, "w": 4, "x": 0, "y": 1 },
      "id": 1,
      "options": {
        "colorMode": "background",
        "graphMode": "none",
        "justifyMode": "center",
        "orientation": "auto",
        "reduceOptions": { "calcs": ["lastNotNull"], "fields": "", "values": false },
        "textMode": "value"
      },
      "title": "Current Tier",
      "type": "stat",
      "targets": [
        {
          "datasource": { "type": "prometheus", "uid": "prometheus" },
          "expr": "dg_current_tier",
          "instant": true,
          "legendFormat": "tier"
        }
      ]
    },
    {
      "datasource": { "type": "prometheus", "uid": "prometheus" },
      "fieldConfig": {
        "defaults": {
          "color": { "mode": "palette-classic" },
          "custom": {
            "axisCenteredZero": false,
            "axisColorMode": "text",
            "axisLabel": "",
            "axisPlacement": "auto",
            "barAlignment": 0,
            "drawStyle": "line",
            "fillOpacity": 10,
            "gradientMode": "none",
            "hideFrom": { "legend": false, "tooltip": false, "viz": false },
            "lineInterpolation": "linear",
            "lineWidth": 2,
            "pointSize": 5,
            "scaleDistribution": { "type": "linear" },
            "showPoints": "never",
            "spanNulls": false,
            "stacking": { "group": "A", "mode": "none" },
            "thresholdsStyle": { "mode": "dashed" }
          },
          "thresholds": {
            "mode": "absolute",
            "steps": [
              { "color": "green", "value": null },
              { "color": "yellow", "value": 800 },
              { "color": "orange", "value": 1500 },
              { "color": "red", "value": 2000 }
            ]
          },
          "unit": "reqps"
        },
        "overrides": []
      },
      "gridPos": { "h": 6, "w": 10, "x": 4, "y": 1 },
      "id": 2,
      "options": {
        "legend": { "calcs": ["lastNotNull", "max"], "displayMode": "table", "placement": "bottom" },
        "tooltip": { "mode": "single", "sort": "none" }
      },
      "title": "RPS Signal",
      "type": "timeseries",
      "targets": [
        {
          "datasource": { "type": "prometheus", "uid": "prometheus" },
          "expr": "dg_signal_value{signal_id=\"rps\"}",
          "legendFormat": "rps"
        }
      ]
    },
    {
      "datasource": { "type": "prometheus", "uid": "prometheus" },
      "fieldConfig": {
        "defaults": {
          "color": { "mode": "palette-classic" },
          "custom": {
            "drawStyle": "line",
            "fillOpacity": 10,
            "lineWidth": 2,
            "pointSize": 5,
            "showPoints": "never",
            "spanNulls": false
          },
          "unit": "ms"
        },
        "overrides": []
      },
      "gridPos": { "h": 6, "w": 10, "x": 14, "y": 1 },
      "id": 3,
      "options": {
        "legend": { "calcs": ["lastNotNull", "max"], "displayMode": "table", "placement": "bottom" },
        "tooltip": { "mode": "single", "sort": "none" }
      },
      "title": "DB Latency P99",
      "type": "timeseries",
      "targets": [
        {
          "datasource": { "type": "prometheus", "uid": "prometheus" },
          "expr": "dg_signal_value{signal_id=\"db_latency_p99\"}",
          "legendFormat": "db_latency_p99"
        }
      ]
    },
    {
      "collapsed": false,
      "gridPos": { "h": 1, "w": 24, "x": 0, "y": 7 },
      "id": 101,
      "title": "Transitions & Gate",
      "type": "row"
    },
    {
      "datasource": { "type": "prometheus", "uid": "prometheus" },
      "fieldConfig": {
        "defaults": {
          "color": { "mode": "palette-classic" },
          "custom": {
            "drawStyle": "bars",
            "fillOpacity": 80,
            "lineWidth": 1,
            "pointSize": 5,
            "showPoints": "never",
            "spanNulls": false
          },
          "unit": "short"
        },
        "overrides": []
      },
      "gridPos": { "h": 6, "w": 12, "x": 0, "y": 8 },
      "id": 4,
      "options": {
        "legend": { "calcs": ["sum"], "displayMode": "table", "placement": "bottom" },
        "tooltip": { "mode": "single", "sort": "none" }
      },
      "title": "Tier Transitions (rate/min)",
      "type": "timeseries",
      "targets": [
        {
          "datasource": { "type": "prometheus", "uid": "prometheus" },
          "expr": "rate(dg_tier_transitions_total[1m])",
          "legendFormat": "{{from_tier}} → {{to_tier}}"
        }
      ]
    },
    {
      "datasource": { "type": "prometheus", "uid": "prometheus" },
      "fieldConfig": {
        "defaults": {
          "color": { "mode": "palette-classic" },
          "custom": {
            "drawStyle": "bars",
            "fillOpacity": 80,
            "lineWidth": 1,
            "showPoints": "never",
            "spanNulls": false
          },
          "unit": "short"
        },
        "overrides": []
      },
      "gridPos": { "h": 6, "w": 12, "x": 12, "y": 8 },
      "id": 5,
      "options": {
        "legend": { "calcs": ["sum"], "displayMode": "table", "placement": "bottom" },
        "tooltip": { "mode": "single", "sort": "none" }
      },
      "title": "Gate Events (rate/min)",
      "type": "timeseries",
      "targets": [
        {
          "datasource": { "type": "prometheus", "uid": "prometheus" },
          "expr": "rate(dg_gate_events_total[1m])",
          "legendFormat": "{{outcome}}"
        }
      ]
    },
    {
      "collapsed": false,
      "gridPos": { "h": 1, "w": 24, "x": 0, "y": 14 },
      "id": 102,
      "title": "Signals — All",
      "type": "row"
    },
    {
      "datasource": { "type": "prometheus", "uid": "prometheus" },
      "fieldConfig": {
        "defaults": {
          "color": { "mode": "palette-classic" },
          "custom": {
            "drawStyle": "line",
            "fillOpacity": 5,
            "lineWidth": 2,
            "showPoints": "never",
            "spanNulls": false
          },
          "unit": "short"
        },
        "overrides": []
      },
      "gridPos": { "h": 7, "w": 12, "x": 0, "y": 15 },
      "id": 6,
      "options": {
        "legend": { "calcs": ["lastNotNull"], "displayMode": "table", "placement": "bottom" },
        "tooltip": { "mode": "multi", "sort": "none" }
      },
      "title": "All Signal Values",
      "type": "timeseries",
      "targets": [
        {
          "datasource": { "type": "prometheus", "uid": "prometheus" },
          "expr": "dg_signal_value",
          "legendFormat": "{{signal_id}}"
        }
      ]
    },
    {
      "datasource": { "type": "prometheus", "uid": "prometheus" },
      "fieldConfig": {
        "defaults": {
          "color": { "mode": "thresholds" },
          "thresholds": {
            "mode": "absolute",
            "steps": [
              { "color": "green", "value": null },
              { "color": "yellow", "value": 100 },
              { "color": "red", "value": 500 }
            ]
          },
          "unit": "short"
        },
        "overrides": []
      },
      "gridPos": { "h": 7, "w": 6, "x": 12, "y": 15 },
      "id": 7,
      "options": {
        "colorMode": "value",
        "graphMode": "area",
        "justifyMode": "center",
        "orientation": "auto",
        "reduceOptions": { "calcs": ["lastNotNull"], "fields": "", "values": false },
        "textMode": "auto"
      },
      "title": "Write Queue Depth",
      "type": "stat",
      "targets": [
        {
          "datasource": { "type": "prometheus", "uid": "prometheus" },
          "expr": "dg_write_queue_depth",
          "legendFormat": "depth"
        }
      ]
    },
    {
      "datasource": { "type": "prometheus", "uid": "prometheus" },
      "fieldConfig": {
        "defaults": {
          "color": { "mode": "thresholds" },
          "thresholds": {
            "mode": "absolute",
            "steps": [
              { "color": "green", "value": null },
              { "color": "red", "value": 1 }
            ]
          },
          "unit": "short"
        },
        "overrides": []
      },
      "gridPos": { "h": 7, "w": 6, "x": 18, "y": 15 },
      "id": 8,
      "options": {
        "colorMode": "value",
        "graphMode": "area",
        "justifyMode": "center",
        "orientation": "auto",
        "reduceOptions": { "calcs": ["lastNotNull"], "fields": "", "values": false },
        "textMode": "auto"
      },
      "title": "Write Queue Dropped",
      "type": "stat",
      "targets": [
        {
          "datasource": { "type": "prometheus", "uid": "prometheus" },
          "expr": "dg_write_queue_dropped_total",
          "legendFormat": "dropped"
        }
      ]
    }
  ],
  "refresh": "5s",
  "schemaVersion": 38,
  "tags": ["iddc", "degradation", "sre"],
  "templating": { "list": [] },
  "time": { "from": "now-15m", "to": "now" },
  "timepicker": {},
  "timezone": "browser",
  "title": "IDDC — Degradation Contracts",
  "uid": "iddc-main",
  "version": 1
}
